Instrument.py
sjkim_Instrument-1.0.0.dist-info/METADATA
sjkim_Instrument-1.0.0.dist-info/WHEEL
sjkim_Instrument-1.0.0.dist-info/top_level.txt
sjkim_Instrument-1.0.0.dist-info/RECORD
