Metadata-Version: 2.1
Name: sjkim-Instrument
Version: 1.0.0
Summary: GPIB instrument SCPI Control library
Home-page: https://ksj10111011.blog.me/
Author: sjkim
Author-email: ksj101110111@gmail.com
License: UNKNOWN
Platform: UNKNOWN
